imopay_wrapper/__init__.py
imopay_wrapper/_version.py
imopay_wrapper/constants.py
imopay_wrapper/exceptions.py
imopay_wrapper/field.py
imopay_wrapper/regex.py
imopay_wrapper/utils.py
imopay_wrapper/validators.py
imopay_wrapper/models/__init__.py
imopay_wrapper/models/address.py
imopay_wrapper/models/bank_account.py
imopay_wrapper/models/base.py
imopay_wrapper/models/company.py
imopay_wrapper/models/person.py
imopay_wrapper/models/transaction.py
imopay_wrapper/models/webhook.py
imopay_wrapper/wrapper/__init__.py
imopay_wrapper/wrapper/address.py
imopay_wrapper/wrapper/bank_account.py
imopay_wrapper/wrapper/base.py
imopay_wrapper/wrapper/company.py
imopay_wrapper/wrapper/person.py
imopay_wrapper/wrapper/transaction.py
imopay_wrapper/wrapper/webhook.py
imopay_wrapper-0.0.10.dist-info/LICENSE
imopay_wrapper-0.0.10.dist-info/METADATA
imopay_wrapper-0.0.10.dist-info/WHEEL
imopay_wrapper-0.0.10.dist-info/top_level.txt
imopay_wrapper-0.0.10.dist-info/RECORD
